pydantic_bind/__init__.py
pydantic_bind/base.py
pydantic_bind/cpp_generator.py
pydantic_bind/include/msgpack/msgpack.h
pydantic_bind-1.0.5.dist-info/LICENSE
pydantic_bind-1.0.5.dist-info/METADATA
pydantic_bind-1.0.5.dist-info/WHEEL
pydantic_bind-1.0.5.dist-info/top_level.txt
pydantic_bind-1.0.5.dist-info/RECORD
